{
  "generated_at": "2026-07-23T21:43:54.506457+00:00",
  "source": "RIPEstat (looking-glass, rpki-validation, bgp-updates, as-overview)",
  "watchlist_size": 2,
  "anomalies": 0,
  "churn_events": 0,
  "signal": 0,
  "events": [
    {
      "event": "OK",
      "prefix": "1.1.1.0/24",
      "origin_asn": 13335,
      "origins_seen": [
        13335
      ],
      "name": "Cloudflare",
      "holder": "CLOUDFLARENET - Cloudflare, Inc.",
      "status": "OK",
      "rpki": "valid",
      "updates_24h": {
        "announcements": 1280,
        "withdrawals": 19
      },
      "updates_per_peer": 3.53,
      "peers_visible": 368,
      "is_security_anomaly": false,
      "severity": 0,
      "ts": "2026-07-23T21:43:54.506354+00:00"
    }
  ]
}